README.md
setup.cfg
setup.py
floodfill/__init__.py
floodfill/floodfill.py
floodfill.egg-info/PKG-INFO
floodfill.egg-info/SOURCES.txt
floodfill.egg-info/dependency_links.txt
floodfill.egg-info/requires.txt
floodfill.egg-info/top_level.txt