Metadata-Version: 1.1
Name: floodfill
Version: 0.0.1
Summary: Python Floating Point Flood Fill Tool
Home-page: https://github.com/cgmorton/flood-fill
Author: Charles Morton
Author-email: charles.g.morton@gmail.com
License: Apache
Download-URL: https://github.com/cgmorton/flood-fill/archive/v0.0.1.tar.gz
Keywords: Flood Fill
Platform: UNKNOWN
Classifier: License :: OSI Approved :: Apache Software License
Classifier: Programming Language :: Python :: 2.7
Classifier: Programming Language :: Python :: 3.5
Classifier: Programming Language :: Python :: 3.6
